dijkstar/__init__.py
dijkstar/algorithm.py
dijkstar/graph.py
dijkstar/tests/__init__.py
dijkstar/tests/test_algorithm.py
dijkstar/tests/test_graph.py
Dijkstar-2.6.0.dist-info/METADATA
Dijkstar-2.6.0.dist-info/WHEEL
Dijkstar-2.6.0.dist-info/top_level.txt
Dijkstar-2.6.0.dist-info/RECORD
