Metadata-Version: 2.1
Name: Dijkstar
Version: 2.6.0
Summary: Dijkstra/A*
Home-page: https://github.com/wylee/Dijkstar
Author: Wyatt Baldwin
Author-email: self@wyattbaldwin.com
License: MIT
Keywords: Dijkstra A* algorithms
Platform: UNKNOWN
Classifier: Development Status :: 4 - Beta
Classifier: Intended Audience :: Developers
Classifier: License :: OSI Approved :: MIT License
Classifier: Natural Language :: English
Classifier: Programming Language :: Python :: 2
Classifier: Programming Language :: Python :: 2.7
Classifier: Programming Language :: Python :: 3
Classifier: Programming Language :: Python :: 3.4
Classifier: Programming Language :: Python :: 3.5
Classifier: Programming Language :: Python :: 3.6
Classifier: Programming Language :: Python :: 3.7
Classifier: Programming Language :: Python :: 3.8
Classifier: Programming Language :: Python :: 3.9
Provides-Extra: dev
